[
    {
        "id": 1,
        "name": "裝設心律調節器、植入式去顫器或其他主動式植入電子裝置者"
    },
    {
        "id": 2,
        "name": "膝蓋急性發炎積水、感染、或有開放性傷口者"
    },
    {
        "id": 3,
        "name": "患部嚴重感覺缺失或無法可靠表達不適之患者"
    },
    {
        "id": 4,
        "name": "深部靜脈血栓、急性發炎或不穩定骨折等急性病症者"
    },
    {
        "id": 5,
        "name": "對電刺激或裝置材料過敏者"
    },
    {
        "id": 6,
        "name": "其他神經肌肉骨骼系統傷病，包含中風病患與明顯膝關節肌腱韌帶受傷者"
    },
    {
        "id": 7,
        "name": "接受過膝關節置換者"
    },
    {
        "id": 8,
        "name": "其他"
    }
]